thznumpy/__init__.py
thznumpy/classes.py
thznumpy/geometry_utils.py
thznumpy/utils/__init__.py
thznumpy/utils/maths.py
thznumpy-0.0.2.dist-info/METADATA
thznumpy-0.0.2.dist-info/WHEEL
thznumpy-0.0.2.dist-info/top_level.txt
thznumpy-0.0.2.dist-info/RECORD
