Metadata-Version: 2.1
Name: thznumpy
Version: 0.0.2
Summary: a math lib developed by Sen
Home-page: https://github.com/tianhuzong/thztnumpy
Author: Sen
Author-email: tianhuzong@qq.com
License: MIT
Platform: UNKNOWN
Classifier: Programming Language :: Python :: 3
Classifier: License :: OSI Approved :: MIT License
Classifier: Operating System :: OS Independent
Requires-Dist: numpy
Requires-Dist: sympy
